Metadata-Version: 2.1
Name: setuptool-file
Version: 0.0.1
Summary: oss-dev my calculator 0001
Home-page: https://github.com/kjune922/github-action
Download-URL: https://github.com/sejin-chun/calc0001.git
Author: kjune922
License: UNKNOWN
Platform: UNKNOWN
Classifier: Programming Language :: Python :: 3
